Metadata-Version: 2.1
Name: UserManage
Version: 0.0.0.4
Summary: Command line Demo
Author: mengqi
License: UNKNOWN
Platform: any
